{
  "authors": [
    "YUUJI Yuuji",
    "Nanasuke"
  ],
  "identifier": "08041258-b956-4d25-83b4-7b5c7dcf7058",
  "type": "manga",
  "page": "Mangadex",
  "title": "Ore no Kanojo to Osananajimi ga Shuraba Sugiru",
  "url": "https://mangadex.org/title/08041258-b956-4d25-83b4-7b5c7dcf7058",
  "image": "https://uploads.mangadex.org/covers/08041258-b956-4d25-83b4-7b5c7dcf7058/2efab6d2-9d32-490a-9771-8598a8a4d6ab.jpg",
  "hentai": false,
  "sticky": false,
  "active": true,
  "actor": null,
  "malId": 26612,
  "aniId": 56612,
  "createdAt": "2020-10-12T16:02:42.000Z",
  "updatedAt": "2021-06-02T08:51:25.000Z",
  "deletedAt": null,
  "Mal": {
    "altTitle": [
      "俺の彼女と幼なじみが修羅場すぎる"
    ],
    "authors": [
      "Yuuji, Yuuji",
      "Nanasuke"
    ],
    "id": 26612,
    "type": "manga",
    "title": "Ore no Kanojo to Osananajimi ga Shuraba sugiru",
    "url": "https://myanimelist.net/manga/26612/Ore_no_Kanojo_to_Osananajimi_ga_Shuraba_sugiru",
    "image": "https://cdn.myanimelist.net/images/manga/3/188875.jpg",
    "category": "Manga",
    "hentai": false,
    "createdAt": "2020-10-12T15:43:26.000Z",
    "updatedAt": "2021-05-27T16:28:52.000Z",
    "deletedAt": null
  },
  "Anilist": {
    "altTitle": [
      "俺の彼女と幼なじみが修羅場すぎる"
    ],
    "authors": [
      "Yuuji Yuuji",
      "Nanasuke"
    ],
    "id": 56612,
    "malId": 26612,
    "type": "manga",
    "title": "Ore no Kanojo to Osananajimi ga Shuraba Sugiru",
    "url": "https://anilist.co/manga/56612",
    "image": "https://s4.anilist.co/file/anilistcdn/media/manga/cover/medium/bx56612-hFVISymMS6lt.jpg",
    "category": "manga",
    "hentai": false,
    "createdAt": "2021-05-20T14:47:04.000Z",
    "updatedAt": "2021-05-20T14:47:04.000Z",
    "deletedAt": null
  },
  "malUrl": "https://myanimelist.net/manga/26612/Ore_no_Kanojo_to_Osananajimi_ga_Shuraba_sugiru"
}