{
  "authors": [
    "Hayashi Fumino"
  ],
  "identifier": "08147b19-8ed6-4e2e-af11-86181c6c5369",
  "type": "manga",
  "page": "Mangadex",
  "title": "Meteor",
  "url": "https://mangadex.org/title/08147b19-8ed6-4e2e-af11-86181c6c5369",
  "image": "https://uploads.mangadex.org/covers/08147b19-8ed6-4e2e-af11-86181c6c5369/74f0c35c-f6d4-40ed-a7f3-8632f41f2d7d.jpg",
  "hentai": false,
  "sticky": false,
  "active": true,
  "actor": null,
  "malId": 21785,
  "aniId": 51785,
  "createdAt": "2020-10-12T16:02:38.000Z",
  "updatedAt": "2021-06-02T08:24:29.000Z",
  "deletedAt": null,
  "Mal": {
    "altTitle": [
      "Meteor",
      "メテオ, Meteo, Meteo the Meteor, The Meteor",
      "メテオ"
    ],
    "authors": [
      "Hayashi, Fumino"
    ],
    "id": 21785,
    "type": "manga",
    "title": "Meteor",
    "url": "https://myanimelist.net/manga/21785/Meteor",
    "image": "https://cdn.myanimelist.net/images/manga/1/35329.jpg",
    "category": "Manga",
    "hentai": false,
    "createdAt": "2020-10-12T15:42:58.000Z",
    "updatedAt": "2021-04-22T11:27:08.000Z",
    "deletedAt": null
  },
  "Anilist": {
    "altTitle": [
      "Meteor",
      "メテオ",
      "メテオ",
      "Meteo",
      "Meteo the Meteor",
      "The Meteor"
    ],
    "authors": [
      "Fumino Hayashi"
    ],
    "id": 51785,
    "malId": 21785,
    "type": "manga",
    "title": "Meteor",
    "url": "https://anilist.co/manga/51785",
    "image": "https://s4.anilist.co/file/anilistcdn/media/manga/cover/medium/21785.jpg",
    "category": "manga",
    "hentai": false,
    "createdAt": "2021-05-20T14:45:45.000Z",
    "updatedAt": "2021-05-20T14:45:45.000Z",
    "deletedAt": null
  },
  "malUrl": "https://myanimelist.net/manga/21785/Meteor"
}