{
  "authors": [
    "Shioroku"
  ],
  "identifier": "1b3f5bbb-e516-4aaa-b73b-3679b22dd9c8",
  "type": "manga",
  "page": "Mangadex",
  "title": "Hajirai no Puffy Nipple",
  "url": "https://mangadex.org/title/1b3f5bbb-e516-4aaa-b73b-3679b22dd9c8",
  "image": "https://uploads.mangadex.org/covers/1b3f5bbb-e516-4aaa-b73b-3679b22dd9c8/19230519-ac21-4d13-99e4-70e0d33bc9e3.jpg",
  "hentai": true,
  "sticky": false,
  "active": true,
  "actor": null,
  "malId": 110022,
  "aniId": 107326,
  "createdAt": "2020-12-21T12:56:07.000Z",
  "updatedAt": "2021-06-08T09:00:45.000Z",
  "deletedAt": null,
  "Mal": {
    "altTitle": [
      "Big Puffy Nipples College Teen",
      "含羞のパフィーニップル"
    ],
    "authors": [
      "Shioroku"
    ],
    "id": 110022,
    "type": "manga",
    "title": "Hajirai no Puffy Nipple",
    "url": "https://myanimelist.net/manga/110022/Hajirai_no_Puffy_Nipple",
    "image": "https://cdn.myanimelist.net/images/manga/3/201470.jpg",
    "category": "Manga",
    "hentai": true,
    "createdAt": "2020-12-21T12:56:07.000Z",
    "updatedAt": "2020-12-21T12:56:07.000Z",
    "deletedAt": null
  },
  "Anilist": {
    "altTitle": [
      "含羞のパフィーニップル",
      "Big Puffy Nipples College Teen"
    ],
    "authors": [
      "Shioroku"
    ],
    "id": 107326,
    "malId": 110022,
    "type": "manga",
    "title": "Hajirai no Puffy Nipple",
    "url": "https://anilist.co/manga/107326",
    "image": "https://s4.anilist.co/file/anilistcdn/media/manga/cover/medium/nx107326-5DYxmAQkMCe0.png",
    "category": "manga",
    "hentai": true,
    "createdAt": "2021-05-20T14:56:08.000Z",
    "updatedAt": "2021-05-20T14:56:08.000Z",
    "deletedAt": null
  },
  "malUrl": "https://myanimelist.net/manga/110022/Hajirai_no_Puffy_Nipple"
}