{
  "authors": [
    "유명"
  ],
  "identifier": "1bcc9bf3-9624-4d9b-a6bb-ec3cc4169047",
  "type": "manga",
  "page": "Mangadex",
  "title": "Hardcore Vanilla",
  "url": "https://mangadex.org/title/1bcc9bf3-9624-4d9b-a6bb-ec3cc4169047",
  "image": "https://uploads.mangadex.org/covers/1bcc9bf3-9624-4d9b-a6bb-ec3cc4169047/327754c4-25b5-4467-82ec-02894cf239fe.jpg",
  "hentai": true,
  "sticky": false,
  "active": true,
  "actor": null,
  "malId": null,
  "aniId": null,
  "createdAt": "2020-10-29T12:44:22.000Z",
  "updatedAt": "2021-06-08T06:03:37.000Z",
  "deletedAt": null,
  "Mal": null,
  "Anilist": null,
  "malUrl": ""
}