{
  "authors": [
    "Kawaisou na Ko"
  ],
  "identifier": "1e5bb092-cd38-44f4-869e-298be74cd0d8",
  "type": "manga",
  "page": "Mangadex",
  "title": "Mahouka Koukou no Rettousei - Deep Snow (Doujinshi)",
  "url": "https://mangadex.org/title/1e5bb092-cd38-44f4-869e-298be74cd0d8",
  "image": "https://uploads.mangadex.org/covers/1e5bb092-cd38-44f4-869e-298be74cd0d8/188a63c3-5120-41fa-ae6d-47ab85c8f838.jpg",
  "hentai": true,
  "sticky": false,
  "active": true,
  "actor": null,
  "malId": null,
  "aniId": null,
  "createdAt": "2020-10-12T16:19:10.000Z",
  "updatedAt": "2021-06-07T21:27:30.000Z",
  "deletedAt": null,
  "Mal": null,
  "Anilist": null,
  "malUrl": ""
}