{
  "authors": [
    "Herokey"
  ],
  "identifier": "3a5dce77-775d-432a-ac56-7da1e0cbc216",
  "type": "manga",
  "page": "Mangadex",
  "title": "Dungeon ni Deai o Motomeru no wa Machigatteiru Darou ka - Bell-kun Gomenyo (Doujinshi)",
  "url": "https://mangadex.org/title/3a5dce77-775d-432a-ac56-7da1e0cbc216",
  "image": "https://uploads.mangadex.org/covers/3a5dce77-775d-432a-ac56-7da1e0cbc216/24b8787a-4f27-42d2-86a6-4abaff59e7b6.jpg",
  "hentai": true,
  "sticky": false,
  "active": true,
  "actor": null,
  "malId": null,
  "aniId": null,
  "createdAt": "2020-10-12T16:14:28.000Z",
  "updatedAt": "2021-06-06T05:27:39.000Z",
  "deletedAt": null,
  "Mal": null,
  "Anilist": null,
  "malUrl": ""
}