{
  "authors": [
    "Momo ( ͡° ͜ʖ ͡°)"
  ],
  "identifier": "3ade4957-f419-42f3-ade5-c085a429822e",
  "type": "manga",
  "page": "Mangadex",
  "title": "Outside The Box",
  "url": "https://mangadex.org/title/3ade4957-f419-42f3-ade5-c085a429822e",
  "image": "https://uploads.mangadex.org/covers/3ade4957-f419-42f3-ade5-c085a429822e/588d674b-1a2d-497f-9ed2-fe1a633b783b.jpg",
  "hentai": false,
  "sticky": false,
  "active": true,
  "actor": null,
  "malId": null,
  "aniId": null,
  "createdAt": "2020-11-01T22:13:48.000Z",
  "updatedAt": "2021-06-08T06:28:26.000Z",
  "deletedAt": null,
  "Mal": null,
  "Anilist": null,
  "malUrl": ""
}