{
  "authors": [
    "Air X Gravity (Circle)",
    "Bibi"
  ],
  "identifier": "4305e923-be7a-43c6-ae89-5584ce49d97d",
  "type": "manga",
  "page": "Mangadex",
  "title": "Sword Art Online - 2-banme Demo 3-banme Demo Ii Kara~ (Desu~) (Doujinshi)",
  "url": "https://mangadex.org/title/4305e923-be7a-43c6-ae89-5584ce49d97d",
  "image": "https://uploads.mangadex.org/covers/4305e923-be7a-43c6-ae89-5584ce49d97d/e6d4de90-702a-4056-b540-d71de828f4c9.jpg",
  "hentai": false,
  "sticky": false,
  "active": true,
  "actor": null,
  "malId": null,
  "aniId": null,
  "createdAt": "2020-10-12T16:07:51.000Z",
  "updatedAt": "2021-06-04T05:42:00.000Z",
  "deletedAt": null,
  "Mal": null,
  "Anilist": null,
  "malUrl": ""
}