{
  "authors": [
    "Matsumoto Noriyuki"
  ],
  "identifier": "6209638d-dc4e-47f0-ad46-2a7912513802",
  "type": "manga",
  "page": "Mangadex",
  "title": "Tsubame - Hidamari Shoujo Kikou",
  "url": "https://mangadex.org/title/6209638d-dc4e-47f0-ad46-2a7912513802",
  "image": "https://uploads.mangadex.org/covers/6209638d-dc4e-47f0-ad46-2a7912513802/c35fe07b-11ee-4704-9888-a8cb5a2b99f3.jpg",
  "hentai": false,
  "sticky": false,
  "active": true,
  "actor": null,
  "malId": 28619,
  "aniId": 58619,
  "createdAt": "2020-10-12T16:02:50.000Z",
  "updatedAt": "2021-06-02T09:47:32.000Z",
  "deletedAt": null,
  "Mal": {
    "altTitle": [
      "つばめ －陽だまり少女紀行－"
    ],
    "authors": [
      "Matsumoto, Noriyuki"
    ],
    "id": 28619,
    "type": "manga",
    "title": "Tsubame: Hidamari Shoujo Kikou",
    "url": "https://myanimelist.net/manga/28619/Tsubame__Hidamari_Shoujo_Kikou",
    "image": "https://cdn.myanimelist.net/images/manga/3/191118.jpg",
    "category": "Manga",
    "hentai": false,
    "createdAt": "2020-10-12T15:43:30.000Z",
    "updatedAt": "2021-05-04T17:32:29.000Z",
    "deletedAt": null
  },
  "Anilist": {
    "altTitle": [
      "つばめ-陽だまり少女紀行-",
      "Tsubame -Hidamari Shoujo Kikou-"
    ],
    "authors": [
      "Noriyuki Matsumoto"
    ],
    "id": 58619,
    "malId": 28619,
    "type": "manga",
    "title": "Tsubame",
    "url": "https://anilist.co/manga/58619",
    "image": "https://s4.anilist.co/file/anilistcdn/media/manga/cover/medium/28619.jpg",
    "category": "manga",
    "hentai": false,
    "createdAt": "2021-05-20T14:47:32.000Z",
    "updatedAt": "2021-05-20T14:47:32.000Z",
    "deletedAt": null
  },
  "malUrl": "https://myanimelist.net/manga/28619/Tsubame__Hidamari_Shoujo_Kikou"
}