{
  "authors": [
    "Yuzuki Ryouta"
  ],
  "identifier": "63c6a6ea-0e1d-4232-bdd7-d829258285e1",
  "type": "manga",
  "page": "Mangadex",
  "title": "Hshs Sasero!!",
  "url": "https://mangadex.org/title/63c6a6ea-0e1d-4232-bdd7-d829258285e1",
  "image": "https://uploads.mangadex.org/covers/63c6a6ea-0e1d-4232-bdd7-d829258285e1/b48db47d-f9af-4969-88ac-cd9d0e4a691a.jpg",
  "hentai": false,
  "sticky": false,
  "active": true,
  "actor": null,
  "malId": 91458,
  "aniId": 86321,
  "createdAt": "2020-10-12T16:08:27.000Z",
  "updatedAt": "2021-06-04T10:11:38.000Z",
  "deletedAt": null,
  "Mal": {
    "altTitle": [
      "Because she is a little girl, I am excited sexually.",
      "Hasuhasu Sasero!!, Let Me Smell You!!",
      "hshsさせろ!!"
    ],
    "authors": [
      "Yuzuki, Ryouta"
    ],
    "id": 91458,
    "type": "manga",
    "title": "Hshs Sasero!!",
    "url": "https://myanimelist.net/manga/91458/Hshs_Sasero",
    "image": "https://cdn.myanimelist.net/images/manga/2/188848.jpg",
    "category": "Manga",
    "hentai": false,
    "createdAt": "2020-10-12T15:46:07.000Z",
    "updatedAt": "2021-05-06T08:03:10.000Z",
    "deletedAt": null
  },
  "Anilist": {
    "altTitle": [
      "Let Me Smell You!!",
      "hshsさせろ!!",
      "はすはすさせろ!!",
      "Hasuhasu Sasero!!",
      "Because She Is a Little Girl I Am Excited Sexually"
    ],
    "authors": [
      "Ryouta Yuzuki"
    ],
    "id": 86321,
    "malId": 91458,
    "type": "manga",
    "title": "Hshs Sasero!!",
    "url": "https://anilist.co/manga/86321",
    "image": "https://s4.anilist.co/file/anilistcdn/media/manga/cover/medium/nx86321-RDupocSTk5s9.jpg",
    "category": "manga",
    "hentai": false,
    "createdAt": "2021-05-20T14:53:36.000Z",
    "updatedAt": "2021-05-20T14:53:36.000Z",
    "deletedAt": null
  },
  "malUrl": "https://myanimelist.net/manga/91458/Hshs_Sasero"
}