{
  "authors": [
    "TENMAYA"
  ],
  "identifier": "78fd0c82-6bf9-4e97-858b-766d34b761b5",
  "type": "manga",
  "page": "Mangadex",
  "title": "Yuri's bizarre adventure",
  "url": "https://mangadex.org/title/78fd0c82-6bf9-4e97-858b-766d34b761b5",
  "image": "https://uploads.mangadex.org/covers/78fd0c82-6bf9-4e97-858b-766d34b761b5/3f7d5006-75ca-4bc5-bf5f-2282981e98df.jpg",
  "hentai": false,
  "sticky": false,
  "active": true,
  "actor": null,
  "malId": null,
  "aniId": null,
  "createdAt": "2020-12-26T22:26:08.000Z",
  "updatedAt": "2021-06-08T09:06:53.000Z",
  "deletedAt": null,
  "Mal": null,
  "Anilist": null,
  "malUrl": ""
}