{
  "authors": [
    "Urasawa Naoki"
  ],
  "identifier": "9047286f-ea5b-475a-84cc-a2533983ffe9",
  "type": "manga",
  "page": "Mangadex",
  "title": "Asadora!",
  "url": "https://mangadex.org/title/9047286f-ea5b-475a-84cc-a2533983ffe9",
  "image": "https://uploads.mangadex.org/covers/9047286f-ea5b-475a-84cc-a2533983ffe9/73e1c898-497b-41b9-b73c-d024c57f2d0e.jpg",
  "hentai": false,
  "sticky": false,
  "active": true,
  "actor": null,
  "malId": 116000,
  "aniId": 104487,
  "createdAt": "2020-10-12T16:14:03.000Z",
  "updatedAt": "2021-06-06T02:04:40.000Z",
  "deletedAt": null,
  "Mal": {
    "altTitle": [
      "Serial Manga Novel Asadora!, Renzoku Manga Shousetsu",
      "あさドラ！"
    ],
    "authors": [
      "Urasawa, Naoki"
    ],
    "id": 116000,
    "type": "manga",
    "title": "Asadora!",
    "url": "https://myanimelist.net/manga/116000/Asadora",
    "image": "https://cdn.myanimelist.net/images/manga/1/219398.jpg",
    "category": "Manga",
    "hentai": false,
    "createdAt": "2020-10-12T15:47:40.000Z",
    "updatedAt": "2021-05-31T13:33:56.000Z",
    "deletedAt": null
  },
  "Anilist": {
    "altTitle": [
      "Asadora!",
      "あさドラ！",
      "Serial Manga Novel Asadora!",
      "Renzoku Manga Shousetsu Asadora!",
      "連続漫画小説 あさドラ！"
    ],
    "authors": [
      "Naoki Urasawa",
      "Thibaud Desbief"
    ],
    "id": 104487,
    "malId": 116000,
    "type": "manga",
    "title": "Asadora!",
    "url": "https://anilist.co/manga/104487",
    "image": "https://s4.anilist.co/file/anilistcdn/media/manga/cover/medium/bx104487-sct3z5M0DttW.png",
    "category": "manga",
    "hentai": false,
    "createdAt": "2021-05-20T14:57:21.000Z",
    "updatedAt": "2021-05-20T14:57:21.000Z",
    "deletedAt": null
  },
  "malUrl": "https://myanimelist.net/manga/116000/Asadora"
}