{
  "authors": [
    "Meiji Chimera (Chibita)",
    "Meiji Chimera (Fujiwara Yuka)"
  ],
  "identifier": "91138703-90bc-4a5c-94b2-32f5f0012aee",
  "type": "manga",
  "page": "Mangadex",
  "title": "Yu-Gi-Oh! - Saikyou Love Battlers!! (Doujinshi)",
  "url": "https://mangadex.org/title/91138703-90bc-4a5c-94b2-32f5f0012aee",
  "image": "https://uploads.mangadex.org/covers/91138703-90bc-4a5c-94b2-32f5f0012aee/d3e291f0-333d-49cf-8f44-31157c236605.jpg",
  "hentai": false,
  "sticky": false,
  "active": true,
  "actor": null,
  "malId": null,
  "aniId": null,
  "createdAt": "2021-02-27T19:43:52.000Z",
  "updatedAt": "2021-06-08T12:01:44.000Z",
  "deletedAt": null,
  "Mal": null,
  "Anilist": null,
  "malUrl": ""
}