{
  "authors": [
    "Takada Yuuzou"
  ],
  "identifier": "92f2d82d-21c2-4bc5-ada0-89bc75a3a17a",
  "type": "manga",
  "page": "Mangadex",
  "title": "3x3 Eyes - Kiseki no Yami no Keiyakusha",
  "url": "https://mangadex.org/title/92f2d82d-21c2-4bc5-ada0-89bc75a3a17a",
  "image": "https://uploads.mangadex.org/covers/92f2d82d-21c2-4bc5-ada0-89bc75a3a17a/4ee78508-4e44-4d12-8bad-3f65bf445fdd.png",
  "hentai": false,
  "sticky": false,
  "active": true,
  "actor": null,
  "malId": 107408,
  "aniId": 109520,
  "createdAt": "2020-10-12T16:13:37.000Z",
  "updatedAt": "2021-06-05T22:43:19.000Z",
  "deletedAt": null,
  "Mal": {
    "altTitle": [
      "Sazan Eyes, Contractor of Deceased Darkness",
      "3×3EYES 鬼籍の闇の契約者"
    ],
    "authors": [
      "Takada, Yuuzo"
    ],
    "id": 107408,
    "type": "manga",
    "title": "3x3 Eyes: Kiseki no Yami no Keiyakusha",
    "url": "https://myanimelist.net/manga/107408/3x3_Eyes__Kiseki_no_Yami_no_Keiyakusha",
    "image": "https://cdn.myanimelist.net/images/manga/1/197447.jpg",
    "category": "Manga",
    "hentai": false,
    "createdAt": "2020-10-12T15:47:06.000Z",
    "updatedAt": "2021-05-19T11:31:44.000Z",
    "deletedAt": null
  },
  "Anilist": {
    "altTitle": [
      "3×3EYES 鬼籍の闇の契約者",
      "Sazan Eyes",
      "Contractor of Deceased Darkness"
    ],
    "authors": [
      "Yuzo Takada"
    ],
    "id": 109520,
    "malId": 107408,
    "type": "manga",
    "title": "3x3 Eyes: Kiseki no Yami no Keiyakusha",
    "url": "https://anilist.co/manga/109520",
    "image": "https://s4.anilist.co/file/anilistcdn/media/manga/cover/medium/bx109520-0lSiGSpuc5eF.jpg",
    "category": "manga",
    "hentai": false,
    "createdAt": "2021-05-20T14:55:54.000Z",
    "updatedAt": "2021-05-20T14:55:54.000Z",
    "deletedAt": null
  },
  "malUrl": "https://myanimelist.net/manga/107408/3x3_Eyes__Kiseki_no_Yami_no_Keiyakusha"
}