{
  "authors": [
    "Eguchi Ren",
    "Futaba Momo"
  ],
  "identifier": "a92fcfb2-27b7-476f-a9d5-4cd557ae39c0",
  "type": "manga",
  "page": "Mangadex",
  "title": "Tondemo Skill de Isekai Hourou Meshi: Sui no Daibouken",
  "url": "https://mangadex.org/title/a92fcfb2-27b7-476f-a9d5-4cd557ae39c0",
  "image": "https://uploads.mangadex.org/covers/a92fcfb2-27b7-476f-a9d5-4cd557ae39c0/03ae290b-217f-458f-8197-ea1bee047bcc.jpg",
  "hentai": false,
  "sticky": false,
  "active": true,
  "actor": null,
  "malId": 117884,
  "aniId": 110946,
  "createdAt": "2020-10-12T16:16:00.000Z",
  "updatedAt": "2021-06-06T18:40:30.000Z",
  "deletedAt": null,
  "Mal": {
    "altTitle": [
      "Campfire Cooking in Another World with My Absurd Skill: Sui's Great Adventure",
      "とんでもスキルで異世界放浪メシ スイの大冒険"
    ],
    "authors": [
      "Eguchi, Ren",
      "Futaba, Momo"
    ],
    "id": 117884,
    "type": "manga",
    "title": "Tondemo Skill de Isekai Hourou Meshi: Sui no Daibouken",
    "url": "https://myanimelist.net/manga/117884/Tondemo_Skill_de_Isekai_Hourou_Meshi__Sui_no_Daibouken",
    "image": "https://cdn.myanimelist.net/images/manga/3/215071.jpg",
    "category": "Manga",
    "hentai": false,
    "createdAt": "2020-10-12T15:47:51.000Z",
    "updatedAt": "2020-12-21T21:27:16.000Z",
    "deletedAt": null
  },
  "Anilist": {
    "altTitle": [
      "とんでもスキルで異世界放浪メシ スイの大冒険",
      "Campfire Cooking in Another World with My Absurd Skill: Sui no Daibouken",
      "Campfire Cooking in Another World with My Absurd Skill: Sui's Great Adventure",
      "Tondemo Skill de Isekai Hourou Meshi Sui no Dai Bouken"
    ],
    "authors": [
      "Momo  Futaba",
      "Ren Eguchi"
    ],
    "id": 110946,
    "malId": 117884,
    "type": "manga",
    "title": "Tondemo Skill de Isekai Hourou Meshi: Sui no Daibouken",
    "url": "https://anilist.co/manga/110946",
    "image": "https://s4.anilist.co/file/anilistcdn/media/manga/cover/medium/bx110946-hQXjRKy8x22w.jpg",
    "category": "manga",
    "hentai": false,
    "createdAt": "2021-05-20T14:57:58.000Z",
    "updatedAt": "2021-05-20T14:57:58.000Z",
    "deletedAt": null
  },
  "malUrl": "https://myanimelist.net/manga/117884/Tondemo_Skill_de_Isekai_Hourou_Meshi__Sui_no_Daibouken"
}