{
  "authors": [
    "Koume Keito",
    "Aneko no Techo"
  ],
  "identifier": "c7a65633-3942-4bcb-9696-3adba71e0830",
  "type": "manga",
  "page": "Mangadex",
  "title": "Gakuen Utopia Manabi Straight! - Manabi Kirakira Hachijoujima!! (Doujinshi)",
  "url": "https://mangadex.org/title/c7a65633-3942-4bcb-9696-3adba71e0830",
  "image": "https://uploads.mangadex.org/covers/c7a65633-3942-4bcb-9696-3adba71e0830/30cef3c6-556b-4be0-8483-b3e11a4b8032.jpg",
  "hentai": true,
  "sticky": false,
  "active": true,
  "actor": null,
  "malId": null,
  "aniId": null,
  "createdAt": "2020-10-12T16:12:35.000Z",
  "updatedAt": "2021-06-05T15:26:08.000Z",
  "deletedAt": null,
  "Mal": null,
  "Anilist": null,
  "malUrl": ""
}