{
  "authors": [
    "HATA Akimi"
  ],
  "identifier": "d8f3dffd-ef94-4f66-9f39-9d3c01aec232",
  "type": "manga",
  "page": "Mangadex",
  "title": "Unrequited Love Bookstore",
  "url": "https://mangadex.org/title/d8f3dffd-ef94-4f66-9f39-9d3c01aec232",
  "image": "https://uploads.mangadex.org/covers/d8f3dffd-ef94-4f66-9f39-9d3c01aec232/96797428-b0cc-4073-9ecb-e540371fa547.jpg",
  "hentai": false,
  "sticky": false,
  "active": true,
  "actor": null,
  "malId": 75649,
  "aniId": 92215,
  "createdAt": "2020-10-12T16:07:39.000Z",
  "updatedAt": "2021-06-04T09:02:17.000Z",
  "deletedAt": null,
  "Mal": {
    "altTitle": [
      "Tejou to Boin, Douka Ichido dake, Gakuran Nugasete xx shite.",
      "かたおもい書店"
    ],
    "authors": [
      "Hata, Akimi"
    ],
    "id": 75649,
    "type": "manga",
    "title": "Kataomoi Shoten",
    "url": "https://myanimelist.net/manga/75649/Kataomoi_Shoten",
    "image": "https://cdn.myanimelist.net/images/manga/4/161009.jpg",
    "category": "Manga",
    "hentai": false,
    "createdAt": "2020-10-12T15:45:23.000Z",
    "updatedAt": "2021-06-04T04:51:27.000Z",
    "deletedAt": null
  },
  "Anilist": {
    "altTitle": [
      "かたおもい書店",
      "Tejou to Boin",
      "Douka Ichido dake",
      "Gakuran Nugasete xx shite."
    ],
    "authors": [
      "Akimi Hata"
    ],
    "id": 92215,
    "malId": 75649,
    "type": "manga",
    "title": "Kataomoi Shoten",
    "url": "https://anilist.co/manga/92215",
    "image": "https://s4.anilist.co/file/anilistcdn/media/manga/cover/medium/bx92215-jIGAYzUK6J5a.jpg",
    "category": "manga",
    "hentai": false,
    "createdAt": "2021-05-20T14:51:45.000Z",
    "updatedAt": "2021-06-04T04:51:27.000Z",
    "deletedAt": null
  },
  "malUrl": "https://myanimelist.net/manga/75649/Kataomoi_Shoten"
}