{
  "authors": [
    "Ishinomori Shotaro"
  ],
  "identifier": "dd60bcb4-7b56-4e99-b776-be85cfd6f7d0",
  "type": "manga",
  "page": "Mangadex",
  "title": "Sabu to Ichi Torimonohikae",
  "url": "https://mangadex.org/title/dd60bcb4-7b56-4e99-b776-be85cfd6f7d0",
  "image": "https://uploads.mangadex.org/covers/dd60bcb4-7b56-4e99-b776-be85cfd6f7d0/81cd0bea-fa14-4354-aaf4-5d1cf79cb069.jpg",
  "hentai": false,
  "sticky": false,
  "active": true,
  "actor": null,
  "malId": 12427,
  "aniId": 42427,
  "createdAt": "2020-10-12T16:04:37.000Z",
  "updatedAt": "2021-06-02T22:15:44.000Z",
  "deletedAt": null,
  "Mal": {
    "externalLinks": [
      {
        "site": "wikipedia",
        "url": "http://ja.wikipedia.org/wiki/%E4%BD%90%E6%AD%A6%E3%81%A8%E5%B8%82%E6%8D%95%E7%89%A9%E6%8E%A7"
      }
    ],
    "altTitle": [
      "Sabu & Ichi's Arrest Warrant",
      "Sabu and Ichi's Detective Stories",
      "佐武と市捕物控"
    ],
    "authors": [
      "Ishinomori, Shoutarou"
    ],
    "id": 12427,
    "type": "manga",
    "title": "Sabu to Ichi Torimono Hikae",
    "url": "https://myanimelist.net/manga/12427/Sabu_to_Ichi_Torimono_Hikae",
    "image": "https://cdn.myanimelist.net/images/manga/3/150162.jpg",
    "category": "Manga",
    "hentai": false,
    "createdAt": "2020-10-12T15:41:46.000Z",
    "updatedAt": "2021-10-21T01:13:42.000Z",
    "deletedAt": null
  },
  "Anilist": {
    "altTitle": [
      "佐武と市捕物控",
      "Sabu and Ichi's Detective Stories",
      "Sabu & Ichi's Arrest Warrant",
      "Relatos de Sabu e Ichi"
    ],
    "externalLinks": [],
    "authors": [
      "Shoutarou Ishinomori"
    ],
    "id": 42427,
    "malId": 12427,
    "type": "manga",
    "title": "Sabu to Ichi Torimono Hikae",
    "url": "https://anilist.co/manga/42427",
    "image": "https://s4.anilist.co/file/anilistcdn/media/manga/cover/medium/bx42427-RbEOS4yNcxbH.jpg",
    "category": "manga",
    "hentai": false,
    "createdAt": "2021-05-20T14:42:22.000Z",
    "updatedAt": "2021-10-01T05:30:52.000Z",
    "deletedAt": null
  },
  "malUrl": "https://myanimelist.net/manga/12427/Sabu_to_Ichi_Torimono_Hikae"
}