{
  "altTitle": [
    "Pukapuka Dudu, Wakate Animator Ikusei Project, 2011 Young Animator Training Project, Anime Mirai 2011, Dudu the Floater, Dudu the Floatie",
    "ぷかぷかジュジュ"
  ],
  "id": 13173,
  "type": "anime",
  "title": "Puka Puka Juju",
  "url": "https://myanimelist.net/anime/13173/Puka_Puka_Juju",
  "image": "https://cdn.myanimelist.net/images/anime/9/40249.jpg",
  "category": "Movie",
  "hentai": false,
  "createdAt": "2020-10-12T15:39:12.000Z",
  "updatedAt": "2021-04-29T13:18:52.000Z",
  "deletedAt": null,
  "Pages": {
    "9anime": {
      "l9x6": {
        "identifier": "l9x6",
        "type": "anime",
        "page": "9anime",
        "title": "Puka Puka Juju",
        "url": "https://9anime.ru/watch/puka-puka-juju.l9x6",
        "image": "https://static.akacdn.ru/files/images/2018/03/3ced3bb88217baa764ee7b27365bbdf2.jpg",
        "hentai": false,
        "sticky": false,
        "active": true,
        "actor": null,
        "malId": 13173,
        "aniId": 13173,
        "createdAt": "2020-10-12T15:53:03.000Z",
        "updatedAt": "2021-05-20T15:21:51.000Z",
        "deletedAt": null
      }
    }
  }
}