{
  "externalLinks": null,
  "altTitle": [
    "Dies irae",
    "Day of Wrath",
    "Dies irae"
  ],
  "id": 32271,
  "type": "anime",
  "title": "Dies Irae",
  "url": "https://myanimelist.net/anime/32271/Dies_Irae",
  "image": "https://cdn.myanimelist.net/images/anime/2/89682.jpg",
  "category": "TV",
  "hentai": false,
  "anidbId": null,
  "createdAt": "2020-10-12T15:39:42.000Z",
  "updatedAt": "2019-09-08T19:34:49.000Z",
  "deletedAt": null,
  "Pages": {
    "9anime": {
      "j6r8": {
        "identifier": "j6r8",
        "type": "anime",
        "page": "9anime",
        "title": "Dies irae",
        "url": "https://9anime.to/watch/dies-irae.j6r8",
        "image": "https://images2-focus-opensocial.googleusercontent.com/gadgets/proxy?container=focus&amp;gadget=a&amp;no_expand=1&amp;refresh=604800&amp;url=http://2.bp.blogspot.com/-YSRggNsxrDs/WFZr8gmoI7I/AAAAAAABTTw/MxZIE7e3_qM/s0/",
        "hentai": false,
        "sticky": false,
        "active": true,
        "actor": null,
        "malId": 32271,
        "aniId": 21555,
        "createdAt": "2020-10-12T15:52:05.000Z",
        "updatedAt": "2021-05-20T15:21:51.000Z",
        "deletedAt": null
      },
      "rk0o": {
        "identifier": "rk0o",
        "type": "anime",
        "page": "9anime",
        "title": "Dies irae (Dub)",
        "url": "https://9anime.to/watch/dies-irae-dub.rk0o",
        "image": "https://images2-focus-opensocial.googleusercontent.com/gadgets/proxy?container=focus&amp;gadget=a&amp;no_expand=1&amp;refresh=604800&amp;url=http://2.bp.blogspot.com/-yNI8aPlb9hc/We_JjsG6ljI/AAAAAAAADSc/hbzmkFWKPmo4YvmVT_6lVg6IlpxcuANEACHMYCw/s0/",
        "hentai": false,
        "sticky": false,
        "active": true,
        "actor": null,
        "malId": 32271,
        "aniId": 21555,
        "createdAt": "2020-10-12T15:55:32.000Z",
        "updatedAt": "2021-05-20T15:21:52.000Z",
        "deletedAt": null
      }
    },
    "Aniwatch": {
      "39": {
        "identifier": "39",
        "type": "anime",
        "page": "Aniwatch",
        "title": "Dies Irae",
        "url": "https://aniwatch.me/anime/39",
        "image": "https://img.aniwatch.me/0E6373C3F739F95206EC05974A9488F4",
        "hentai": false,
        "sticky": false,
        "active": true,
        "actor": null,
        "malId": 32271,
        "aniId": 21555,
        "createdAt": "2020-10-12T15:57:20.000Z",
        "updatedAt": "2021-05-20T15:21:53.000Z",
        "deletedAt": null
      }
    },
    "Gogoanime": {
      "dies-irae": {
        "identifier": "dies-irae",
        "type": "anime",
        "page": "Gogoanime",
        "title": "Dies Irae",
        "url": "https://gogoanime.vc/category/dies-irae",
        "image": "https://images.gogoanime.tv/cover/dies-irae.png",
        "hentai": false,
        "sticky": false,
        "active": true,
        "actor": null,
        "malId": 32271,
        "aniId": 21555,
        "createdAt": "2020-10-12T16:00:15.000Z",
        "updatedAt": "2021-05-20T15:21:54.000Z",
        "deletedAt": null
      },
      "dies-irae-dub": {
        "identifier": "dies-irae-dub",
        "type": "anime",
        "page": "Gogoanime",
        "title": "Dies Irae (Dub)",
        "url": "https://gogoanime.vc/category/dies-irae-dub",
        "image": "https://cdnimg.xyz/cover/dies-irae-dub.png",
        "hentai": false,
        "sticky": false,
        "active": true,
        "actor": null,
        "malId": 32271,
        "aniId": 21555,
        "createdAt": "2020-10-12T16:00:15.000Z",
        "updatedAt": "2021-05-20T15:21:54.000Z",
        "deletedAt": null
      }
    },
    "animepahe": {
      "2287": {
        "identifier": "2287",
        "type": "anime",
        "page": "animepahe",
        "title": "Dies Irae",
        "url": "https://pahe.win/a/2287",
        "image": "https://i.animepahe.com/posters/f9d97735f528280fc26782b2fa62b659.jpg",
        "hentai": false,
        "sticky": false,
        "active": true,
        "actor": null,
        "malId": 32271,
        "aniId": 21555,
        "createdAt": "2021-03-26T02:19:07.000Z",
        "updatedAt": "2021-05-20T15:25:21.000Z",
        "deletedAt": null
      }
    }
  }
}