{
  "altTitle": [
    "Yuuki Yuuna is a Hero Club Member, Washio Sumi wa Yuusha de Aru",
    "結城友奈は勇者部所属"
  ],
  "id": 35473,
  "type": "anime",
  "title": "Yuuki Yuuna wa Yuushabu Shozoku 3",
  "url": "https://myanimelist.net/anime/35473/Yuuki_Yuuna_wa_Yuushabu_Shozoku_3",
  "image": "https://cdn.myanimelist.net/images/anime/5/85507.jpg",
  "category": "Movie",
  "hentai": false,
  "createdAt": "2020-10-12T15:39:54.000Z",
  "updatedAt": "2021-05-01T03:33:21.000Z",
  "deletedAt": null,
  "Pages": {
    "9anime": {
      "mnkz": {
        "identifier": "mnkz",
        "type": "anime",
        "page": "9anime",
        "title": "Yuuki Yuuna wa Yuusha-bu Shozoku 3",
        "url": "https://9anime.ru/watch/yuuki-yuuna-wa-yuusha-bu-shozoku-3.mnkz",
        "image": "https://static.akacdn.ru/static/images/2018/04/02cd8672159dc00495f74be329c7f3be.jpg",
        "hentai": false,
        "sticky": false,
        "active": true,
        "actor": null,
        "malId": 35473,
        "aniId": 100981,
        "createdAt": "2020-10-12T15:53:33.000Z",
        "updatedAt": "2021-05-20T15:21:52.000Z",
        "deletedAt": null
      }
    }
  }
}