{
  "altTitle": [
    "Puni Puni Poemy",
    "ぷにぷに☆ぽえみぃ"
  ],
  "id": 564,
  "type": "anime",
  "title": "Puni Puni☆Poemii",
  "url": "https://myanimelist.net/anime/564/Puni_Puni☆Poemii",
  "image": "https://cdn.myanimelist.net/images/anime/2/20464.jpg",
  "category": "OVA",
  "hentai": false,
  "createdAt": "2020-10-12T15:38:05.000Z",
  "updatedAt": "2021-04-12T17:47:29.000Z",
  "deletedAt": null,
  "Pages": {
    "9anime": {
      "88zq": {
        "identifier": "88zq",
        "type": "anime",
        "page": "9anime",
        "title": "Puni Puni☆Poemii (Dub)",
        "url": "https://9anime.ru/watch/puni-punipoemii-dub.88zq",
        "image": "https://images2-focus-opensocial.googleusercontent.com/gadgets/proxy?container=focus&amp;gadget=a&amp;no_expand=1&amp;refresh=604800&amp;url=http://2.bp.blogspot.com/-KfvXEhWJqvk/WOYSOx1PBoI/AAAAAAAAf1U/joR18hcZfvc/s0/",
        "hentai": false,
        "sticky": false,
        "active": true,
        "actor": null,
        "malId": 564,
        "aniId": 564,
        "createdAt": "2020-10-12T15:51:27.000Z",
        "updatedAt": "2021-05-20T15:21:51.000Z",
        "deletedAt": null
      },
      "99zn": {
        "identifier": "99zn",
        "type": "anime",
        "page": "9anime",
        "title": "Puni Puni☆Poemii",
        "url": "https://9anime.ru/watch/puni-punipoemii.99zn",
        "image": "https://images2-focus-opensocial.googleusercontent.com/gadgets/proxy?container=focus&amp;gadget=a&amp;no_expand=1&amp;refresh=604800&amp;url=http://2.bp.blogspot.com/-I-2pEXOzOKk/WOYSO8PWPEI/AAAAAAAAf1Y/HDupHY_lGmY/s0/",
        "hentai": false,
        "sticky": false,
        "active": true,
        "actor": null,
        "malId": 564,
        "aniId": 564,
        "createdAt": "2020-10-12T15:51:46.000Z",
        "updatedAt": "2021-05-20T15:21:51.000Z",
        "deletedAt": null
      }
    },
    "Gogoanime": {
      "puni-punipoemii-dub": {
        "identifier": "puni-punipoemii-dub",
        "type": "anime",
        "page": "Gogoanime",
        "title": "Puni Puni☆Poemii (Dub)",
        "url": "https://gogoanime.ai/category/puni-punipoemii-dub",
        "image": "https://gogocdn.net/cover/puni-punipoemii-dub.png",
        "hentai": false,
        "sticky": false,
        "active": true,
        "actor": null,
        "malId": 564,
        "aniId": 564,
        "createdAt": "2021-04-14T16:47:30.000Z",
        "updatedAt": "2021-05-20T15:25:21.000Z",
        "deletedAt": null
      }
    }
  }
}