{
  "externalLinks": null,
  "altTitle": [
    "Police in a Pod",
    "ハコヅメ ～交番女子の逆襲～"
  ],
  "authors": [
    "Yasu, Miko"
  ],
  "id": 111356,
  "type": "manga",
  "title": "Hakozume: Koban Joshi no Gyakushuu",
  "url": "https://myanimelist.net/manga/111356/Hakozume__Koban_Joshi_no_Gyakushuu",
  "image": "https://cdn.myanimelist.net/images/manga/3/209559.jpg",
  "category": "Manga",
  "hentai": false,
  "createdAt": "2020-12-02T22:52:44.000Z",
  "updatedAt": "2021-08-16T19:09:22.000Z",
  "deletedAt": null,
  "Pages": {
    "Mangadex": {
      "563355c9-65cc-4011-8665-15bdc013d00a": {
        "authors": [
          "Yasu Miko"
        ],
        "identifier": "563355c9-65cc-4011-8665-15bdc013d00a",
        "type": "manga",
        "page": "Mangadex",
        "title": "Hakozume ~ Koban Joshi no Gyakushu",
        "url": "https://mangadex.org/title/563355c9-65cc-4011-8665-15bdc013d00a",
        "image": "https://uploads.mangadex.org/covers/563355c9-65cc-4011-8665-15bdc013d00a/fe944401-1ba0-4cd7-b546-84a65e9cbfde.jpg",
        "hentai": false,
        "sticky": false,
        "active": true,
        "actor": null,
        "malId": 111356,
        "aniId": 114732,
        "createdAt": "2020-12-02T22:52:44.000Z",
        "updatedAt": "2021-12-08T08:35:50.000Z",
        "deletedAt": null
      }
    },
    "MangaSee": {
      "police-in-a-pod": {
        "authors": [
          "YASU Miko"
        ],
        "identifier": "police-in-a-pod",
        "type": "manga",
        "page": "MangaSee",
        "title": "Police in a Pod",
        "url": "https://mangasee123.com/manga/Police-in-a-Pod",
        "image": "https://cover.nep.li/cover/Police-in-a-Pod.jpg",
        "hentai": false,
        "sticky": false,
        "active": true,
        "actor": null,
        "malId": 111356,
        "aniId": 114732,
        "createdAt": "2021-08-16T19:09:16.000Z",
        "updatedAt": "2021-08-16T19:37:00.000Z",
        "deletedAt": null
      }
    }
  }
}