{
  "authors": [
    "Matsuura",
    "OOHORI Yutaka"
  ],
  "identifier": "dad-is-a-hero-mom-is-a-spirit-im-a-reincarnator",
  "type": "manga",
  "page": "MangaSee",
  "title": "Dad Is a Hero, Mom Is a Spirit, I'm a Reincarnator",
  "url": "https://mangasee123.com/manga/Dad-Is-a-Hero-Mom-Is-a-Spirit-Im-a-Reincarnator",
  "image": "https://cover.nep.li/cover/Dad-Is-a-Hero-Mom-Is-a-Spirit-Im-a-Reincarnator.jpg",
  "hentai": false,
  "sticky": false,
  "active": true,
  "actor": 1,
  "malId": 119656,
  "aniId": 107980,
  "createdAt": "2021-02-07T03:23:06.000Z",
  "updatedAt": "2021-05-20T15:40:31.000Z",
  "deletedAt": null,
  "Mal": {
    "altTitle": [
      "Dad is a Hero, Mom is a Spirit, I'm a Reincarnator",
      "父は英雄、母は精霊、娘の私は転生者。"
    ],
    "authors": [
      "Oohori, Yutaka",
      "Matsuura"
    ],
    "id": 119656,
    "type": "manga",
    "title": "Chichi wa Eiyuu, Haha wa Seirei, Musume no Watashi wa Tenseisha.",
    "url": "https://myanimelist.net/manga/119656/Chichi_wa_Eiyuu_Haha_wa_Seirei_Musume_no_Watashi_wa_Tenseisha",
    "image": "https://cdn.myanimelist.net/images/manga/3/221517.jpg",
    "category": "Manga",
    "hentai": false,
    "createdAt": "2020-10-12T15:47:57.000Z",
    "updatedAt": "2021-05-29T20:12:12.000Z",
    "deletedAt": null
  },
  "Anilist": {
    "altTitle": [
      "父は英雄、母は精霊、娘の私は転生者。",
      "My Father is a Hero, my Mother is a Spirit and the Daughter (Me) is a Reincarnator.",
      "Dad Is a Hero, Mom Is a Spirit, I'm a Reincarnator"
    ],
    "authors": [
      "keepout",
      "Yutaka Oohori",
      "Matsuura "
    ],
    "id": 107980,
    "malId": 119656,
    "type": "manga",
    "title": "Chichi wa Eiyuu, Haha wa Seirei, Musume no Watashi wa Tenseisha.",
    "url": "https://anilist.co/manga/107980",
    "image": "https://s4.anilist.co/file/anilistcdn/media/manga/cover/medium/bx107980-nA99veQeNpoA.png",
    "category": "manga",
    "hentai": false,
    "createdAt": "2021-05-20T14:58:09.000Z",
    "updatedAt": "2021-05-20T14:58:09.000Z",
    "deletedAt": null
  },
  "malUrl": "https://myanimelist.net/manga/119656/Chichi_wa_Eiyuu_Haha_wa_Seirei_Musume_no_Watashi_wa_Tenseisha"
}