{
  "authors": [
    "Nasty Cat"
  ],
  "identifier": "living-with-one-leg",
  "type": "manga",
  "page": "MangaSee",
  "title": "Living With One Leg",
  "url": "https://mangasee123.com/manga/Living-With-One-Leg",
  "image": "https://cover.nep.li/cover/Living-With-One-Leg.jpg",
  "hentai": false,
  "sticky": false,
  "active": true,
  "actor": null,
  "malId": null,
  "aniId": null,
  "createdAt": "2021-08-08T07:45:18.000Z",
  "updatedAt": "2021-08-08T07:45:18.000Z",
  "deletedAt": null,
  "Mal": null,
  "Anilist": null,
  "malUrl": ""
}