{
  "authors": [
    "KATAKURA Masanori"
  ],
  "identifier": "mahou-tsukai-kurohime",
  "type": "manga",
  "page": "MangaSee",
  "title": "Mahou Tsukai Kurohime",
  "url": "https://mangasee123.com/manga/Mahou-Tsukai-Kurohime",
  "image": "https://cover.nep.li/cover/Mahou-Tsukai-Kurohime.jpg",
  "hentai": false,
  "sticky": false,
  "active": true,
  "actor": null,
  "malId": 893,
  "aniId": 30893,
  "createdAt": "2021-03-24T16:19:13.000Z",
  "updatedAt": "2021-05-20T15:39:24.000Z",
  "deletedAt": null,
  "Mal": {
    "altTitle": [
      "Kurohime",
      "Black Princess",
      "魔砲使い 黒姫"
    ],
    "authors": [
      "Katakura, Masanori"
    ],
    "id": 893,
    "type": "manga",
    "title": "Mahou Tsukai Kurohime",
    "url": "https://myanimelist.net/manga/893/Mahou_Tsukai_Kurohime",
    "image": "https://cdn.myanimelist.net/images/manga/2/143957.jpg",
    "category": "Manga",
    "hentai": false,
    "createdAt": "2020-10-12T15:40:27.000Z",
    "updatedAt": "2021-03-24T16:19:03.000Z",
    "deletedAt": null
  },
  "Anilist": {
    "altTitle": [
      "Kurohime",
      "魔砲使い黒姫",
      "Black Princess",
      "Magic User Black Princess"
    ],
    "authors": [
      "Masanori Katakura"
    ],
    "id": 30893,
    "malId": 893,
    "type": "manga",
    "title": "Mahou Tsukai Kurohime",
    "url": "https://anilist.co/manga/30893",
    "image": "https://s4.anilist.co/file/anilistcdn/media/manga/cover/medium/bx30893-vGmzayqp3uoG.png",
    "category": "manga",
    "hentai": false,
    "createdAt": "2021-05-20T14:35:46.000Z",
    "updatedAt": "2021-05-20T14:35:46.000Z",
    "deletedAt": null
  },
  "malUrl": "https://myanimelist.net/manga/893/Mahou_Tsukai_Kurohime"
}