{
  "authors": [
    "HERO",
    "KOUGYOKU Iduki"
  ],
  "identifier": "seishun-rikon",
  "type": "manga",
  "page": "MangaSee",
  "title": "Seishun Rikon",
  "url": "https://mangasee123.com/manga/Seishun-Rikon",
  "image": "https://cover.nep.li/cover/Seishun-Rikon.jpg",
  "hentai": false,
  "sticky": false,
  "active": true,
  "actor": null,
  "malId": 45089,
  "aniId": 75089,
  "createdAt": "2021-03-13T14:09:22.000Z",
  "updatedAt": "2021-05-20T15:40:19.000Z",
  "deletedAt": null,
  "Mal": {
    "altTitle": [
      "青春離婚"
    ],
    "authors": [
      "HERO",
      "Kougyoku, Iduki"
    ],
    "id": 45089,
    "type": "manga",
    "title": "Seishun Rikon",
    "url": "https://myanimelist.net/manga/45089/Seishun_Rikon",
    "image": "https://cdn.myanimelist.net/images/manga/2/80159.jpg",
    "category": "Manga",
    "hentai": false,
    "createdAt": "2020-10-12T15:44:20.000Z",
    "updatedAt": "2021-04-05T14:08:36.000Z",
    "deletedAt": null
  },
  "Anilist": {
    "altTitle": [
      "青春離婚"
    ],
    "authors": [
      "Hiroki Adachi",
      "Izuki Kougyoku"
    ],
    "id": 75089,
    "malId": 45089,
    "type": "manga",
    "title": "Seishun Rikon",
    "url": "https://anilist.co/manga/75089",
    "image": "https://s4.anilist.co/file/anilistcdn/media/manga/cover/medium/bx75089-35TXzYK9Ox0e.png",
    "category": "manga",
    "hentai": false,
    "createdAt": "2021-05-20T14:49:26.000Z",
    "updatedAt": "2021-05-20T14:49:26.000Z",
    "deletedAt": null
  },
  "malUrl": "https://myanimelist.net/manga/45089/Seishun_Rikon"
}