{
  "altTitle": [
    "ちびねこトムの大冒険 地球を救え！なかまたち",
    "Tomcat's Big Adventure"
  ],
  "externalLinks": [],
  "id": 17657,
  "malId": 17657,
  "type": "anime",
  "title": "Chibi Neko Tom no Daibouken: Chikyuu wo Sukue! Nakama-tachi",
  "url": "https://anilist.co/anime/17657",
  "image": "https://s4.anilist.co/file/anilistcdn/media/anime/cover/medium/bx17657-IyRO1smIDpvG.png",
  "category": "special",
  "hentai": false,
  "createdAt": "2021-10-10T01:02:20.000Z",
  "updatedAt": "2021-10-10T01:02:20.000Z",
  "deletedAt": null,
  "Pages": {}
}