{
  "altTitle": [
    "Wizard Barristers",
    "ウィザード・バリスターズ〜弁魔士セシル"
  ],
  "id": 20053,
  "malId": 20053,
  "type": "anime",
  "title": "Wizard Barristers: Benmashi Cecil",
  "url": "https://anilist.co/anime/20053",
  "image": "https://s4.anilist.co/file/anilistcdn/media/anime/cover/medium/bx20053-PIdMAmmoFI6l.jpg",
  "category": "tv",
  "hentai": false,
  "createdAt": "2021-05-20T14:40:36.000Z",
  "updatedAt": "2021-05-20T14:40:36.000Z",
  "deletedAt": null,
  "Pages": {
    "9anime": {
      "5y50": {
        "identifier": "5y50",
        "type": "anime",
        "page": "9anime",
        "title": "Wizard Barristers: Benmashi Cecil (Dub)",
        "url": "https://9anime.ru/watch/wizard-barristers-benmashi-cecil-dub.5y50",
        "image": "https://images2-focus-opensocial.googleusercontent.com/gadgets/proxy?container=focus&amp;gadget=a&amp;no_expand=1&amp;refresh=604800&amp;url=http://2.bp.blogspot.com/-uhcsWNaLaIU/WEqLa8FzgBI/AAAAAAABSAs/6XzOHX6eR7U/s0/",
        "hentai": false,
        "sticky": false,
        "active": true,
        "actor": null,
        "malId": 20053,
        "aniId": 20053,
        "createdAt": "2020-10-12T15:50:38.000Z",
        "updatedAt": "2021-05-20T15:21:51.000Z",
        "deletedAt": null
      },
      "rwlo": {
        "identifier": "rwlo",
        "type": "anime",
        "page": "9anime",
        "title": "Wizard Barristers: Benmashi Cecil",
        "url": "https://9anime.ru/watch/wizard-barristers-benmashi-cecil.rwlo",
        "image": "https://images2-focus-opensocial.googleusercontent.com/gadgets/proxy?container=focus&amp;gadget=a&amp;no_expand=1&amp;refresh=604800&amp;url=http://2.bp.blogspot.com/-60OjeFha8wQ/V6nOW6USsdI/AAAAAAAA1uE/PxUchrbqlPU/s0/",
        "hentai": false,
        "sticky": false,
        "active": true,
        "actor": null,
        "malId": 20053,
        "aniId": 20053,
        "createdAt": "2020-10-12T15:55:39.000Z",
        "updatedAt": "2021-05-20T15:21:52.000Z",
        "deletedAt": null
      }
    },
    "Aniwatch": {
      "2658": {
        "identifier": "2658",
        "type": "anime",
        "page": "Aniwatch",
        "title": "Wizard Barristers: Benmashi Cecil",
        "url": "https://aniwatch.me/anime/2658",
        "image": "-",
        "hentai": false,
        "sticky": false,
        "active": true,
        "actor": null,
        "malId": 20053,
        "aniId": 20053,
        "createdAt": "2020-10-12T15:58:31.000Z",
        "updatedAt": "2021-05-20T15:21:53.000Z",
        "deletedAt": null
      }
    },
    "Twistmoe": {
      "wizard-barristers-benmashi-cecil": {
        "identifier": "wizard-barristers-benmashi-cecil",
        "type": "anime",
        "page": "Twistmoe",
        "title": "Wizard Barristers: Benmashi Cecil",
        "url": "https://twist.moe/a/wizard-barristers-benmashi-cecil/1",
        "image": "-",
        "hentai": false,
        "sticky": false,
        "active": true,
        "actor": null,
        "malId": 20053,
        "aniId": 20053,
        "createdAt": "2020-10-12T16:27:24.000Z",
        "updatedAt": "2021-05-20T15:21:55.000Z",
        "deletedAt": null
      }
    },
    "animepahe": {
      "290": {
        "identifier": "290",
        "type": "anime",
        "page": "animepahe",
        "title": "Wizard Barristers: Benmashi Cecil",
        "url": "https://pahe.win/a/290",
        "image": "https://i.animepahe.com/posters/8d68aa9b01c3107917b856a92a5dbc4a.jpg",
        "hentai": false,
        "sticky": false,
        "active": true,
        "actor": null,
        "malId": 20053,
        "aniId": 20053,
        "createdAt": "2020-11-01T20:17:52.000Z",
        "updatedAt": "2021-05-20T15:21:57.000Z",
        "deletedAt": null
      }
    },
    "Gogoanime": {
      "wizard-barristers-benmashi-cecil": {
        "identifier": "wizard-barristers-benmashi-cecil",
        "type": "anime",
        "page": "Gogoanime",
        "title": "Wizard Barristers: Benmashi Cecil",
        "url": "https://gogoanime.so/category/wizard-barristers-benmashi-cecil",
        "image": "https://gogocdn.net/images/anime/W/Wizard Barristers Benmashi Cecil.jpg",
        "hentai": false,
        "sticky": false,
        "active": true,
        "actor": null,
        "malId": 20053,
        "aniId": 20053,
        "createdAt": "2020-11-25T16:02:10.000Z",
        "updatedAt": "2021-05-20T15:21:57.000Z",
        "deletedAt": null
      },
      "wizard-barristers-benmashi-cecil-dub": {
        "identifier": "wizard-barristers-benmashi-cecil-dub",
        "type": "anime",
        "page": "Gogoanime",
        "title": "Wizard Barristers: Benmashi Cecil (Dub)",
        "url": "https://gogoanime.ai/category/wizard-barristers-benmashi-cecil-dub",
        "image": "https://gogocdn.net/cover/wizard-barristers-benmashi-cecil-dub.png",
        "hentai": false,
        "sticky": false,
        "active": true,
        "actor": null,
        "malId": 20053,
        "aniId": 20053,
        "createdAt": "2021-05-02T09:03:54.000Z",
        "updatedAt": "2021-05-20T15:25:21.000Z",
        "deletedAt": null
      }
    }
  }
}