{
  "altTitle": [
    "Yu-Gi-Oh! VRAINS",
    "遊☆戯☆王VRAINS"
  ],
  "id": 98231,
  "malId": 34866,
  "type": "anime",
  "title": "Yu☆Gi☆Oh! VRAINS",
  "url": "https://anilist.co/anime/98231",
  "image": "https://s4.anilist.co/file/anilistcdn/media/anime/cover/medium/bx98231-mPVCPWmg3KiL.png",
  "category": "tv",
  "hentai": false,
  "createdAt": "2021-05-20T14:43:23.000Z",
  "updatedAt": "2021-05-20T14:43:23.000Z",
  "deletedAt": null,
  "Pages": {
    "9anime": {
      "r8mp": {
        "identifier": "r8mp",
        "type": "anime",
        "page": "9anime",
        "title": "Yu☆Gi☆Oh! VRAINS",
        "url": "https://9anime.ru/watch/yugioh-vrains.r8mp",
        "image": "https://images2-focus-opensocial.googleusercontent.com/gadgets/proxy?container=focus&amp;gadget=a&amp;no_expand=1&amp;refresh=604800&amp;url=http://2.bp.blogspot.com/-f5dYA2Km-p8/WQASwjvOBaI/AAAAAAAAkak/b24JcKLH9NMCK2OUR0Bn9VjSfxGglSMJACHM/s0/",
        "hentai": false,
        "sticky": false,
        "active": true,
        "actor": null,
        "malId": 34866,
        "aniId": 98231,
        "createdAt": "2020-10-12T15:55:30.000Z",
        "updatedAt": "2021-05-20T15:21:52.000Z",
        "deletedAt": null
      },
      "wm6l": {
        "identifier": "wm6l",
        "type": "anime",
        "page": "9anime",
        "title": "Yu-Gi-Oh! VRAINS (Dub)",
        "url": "https://9anime.ru/watch/yu-gi-oh-vrains-dub.wm6l",
        "image": "http://static.akacdn.ru/static/images/2018/03/4e26d7a2067f8bea7d33e701449d4dda.jpg",
        "hentai": false,
        "sticky": false,
        "active": true,
        "actor": null,
        "malId": 34866,
        "aniId": 98231,
        "createdAt": "2020-10-12T15:56:10.000Z",
        "updatedAt": "2021-05-20T15:21:52.000Z",
        "deletedAt": null
      }
    },
    "Aniwatch": {
      "70": {
        "identifier": "70",
        "type": "anime",
        "page": "Aniwatch",
        "title": "Yu-Gi-Oh! VRAINS",
        "url": "https://aniwatch.me/anime/70",
        "image": "https://img.aniwatch.me/357204DDEF221308242981ECE37C728A",
        "hentai": false,
        "sticky": false,
        "active": true,
        "actor": null,
        "malId": 34866,
        "aniId": 98231,
        "createdAt": "2020-10-12T15:57:21.000Z",
        "updatedAt": "2021-05-20T15:21:53.000Z",
        "deletedAt": null
      }
    },
    "Gogoanime": {
      "yu-gi-oh-vrains": {
        "identifier": "yu-gi-oh-vrains",
        "type": "anime",
        "page": "Gogoanime",
        "title": "Yu-Gi-Oh! VRAINS",
        "url": "https://gogoanime.so/category/yu-gi-oh-vrains",
        "image": "https://images.gogoanime.tv/cover/yu-gi-oh-vrains.png",
        "hentai": false,
        "sticky": false,
        "active": true,
        "actor": null,
        "malId": 34866,
        "aniId": 98231,
        "createdAt": "2020-10-12T16:02:20.000Z",
        "updatedAt": "2021-05-20T15:21:55.000Z",
        "deletedAt": null
      },
      "yugioh-vrains-dub": {
        "identifier": "yugioh-vrains-dub",
        "type": "anime",
        "page": "Gogoanime",
        "title": "Yu☆Gi☆Oh! VRAINS (Dub)",
        "url": "https://gogoanime.so/category/yugioh-vrains-dub",
        "image": "https://gogocdn.net/cover/yugioh-vrains-dub.png",
        "hentai": false,
        "sticky": false,
        "active": true,
        "actor": null,
        "malId": 34866,
        "aniId": 98231,
        "createdAt": "2021-01-29T05:18:01.000Z",
        "updatedAt": "2021-05-20T15:25:21.000Z",
        "deletedAt": null
      }
    },
    "animepahe": {
      "2030": {
        "identifier": "2030",
        "type": "anime",
        "page": "animepahe",
        "title": "Yu☆Gi☆Oh! VRAINS",
        "url": "https://pahe.win/a/2030",
        "image": "https://i.animepahe.com/posters/e153af43266b68396e71c6299754ce49.jpg",
        "hentai": false,
        "sticky": false,
        "active": true,
        "actor": null,
        "malId": 34866,
        "aniId": 98231,
        "createdAt": "2021-02-27T03:44:13.000Z",
        "updatedAt": "2021-05-20T15:25:21.000Z",
        "deletedAt": null
      }
    },
    "Crunchyroll": {
      "yu-gi-oh!%20vrains": {
        "identifier": "yu-gi-oh!%20vrains",
        "type": "anime",
        "page": "Crunchyroll",
        "title": "Yu-Gi-Oh! VRAINS",
        "url": "https://www.crunchyroll.com/yu-gi-oh-vrains?media_id=737197",
        "image": "https://img1.ak.crunchyroll.com/i/spire1-tmb/9be12ed98c59650b5d7d4b901c289b6f1496342996_full.jpg",
        "hentai": false,
        "sticky": false,
        "active": true,
        "actor": null,
        "malId": 34866,
        "aniId": 98231,
        "createdAt": "2021-04-21T23:57:11.000Z",
        "updatedAt": "2021-05-20T15:25:21.000Z",
        "deletedAt": null
      }
    }
  }
}