{
  "authors": [
    "RYUUMON Ryou"
  ],
  "identifier": "bloody_monday",
  "type": "manga",
  "page": "MangaFox",
  "title": "Bloody Monday",
  "url": "https://fanfox.net/manga/bloody_monday/",
  "image": "https://fmcdn.mfcdn.net/store/manga/1277/cover.jpg",
  "hentai": false,
  "sticky": false,
  "active": true,
  "actor": null,
  "malId": null,
  "aniId": null,
  "createdAt": "2021-03-24T17:49:35.000Z",
  "updatedAt": "2021-03-24T17:49:35.000Z",
  "deletedAt": null,
  "Mal": null,
  "Anilist": null,
  "malUrl": ""
}