{
  "authors": [
    "Kemu"
  ],
  "identifier": "the_girl_who_will_let_you_do_what_you_want",
  "type": "manga",
  "page": "MangaFox",
  "title": "The Girl Who Will Let You Do What You Want",
  "url": "https://fanfox.net/manga/the_girl_who_will_let_you_do_what_you_want/",
  "image": "https://fmcdn.mfcdn.net/store/manga/28859/cover.jpg",
  "hentai": false,
  "sticky": false,
  "active": true,
  "actor": null,
  "malId": null,
  "aniId": null,
  "createdAt": "2021-03-16T08:02:54.000Z",
  "updatedAt": "2021-03-16T08:02:54.000Z",
  "deletedAt": null,
  "Mal": null,
  "Anilist": null,
  "malUrl": ""
}