{
  "authors": [
    "Updating"
  ],
  "identifier": "manga-mf990140",
  "type": "manga",
  "page": "MangaNato",
  "title": "The Princess Doesn’T Want To Marry Her Ideal Type",
  "url": "https://manganato.com/manga-mf990140",
  "image": "https://avt.mkklcdnv6temp.com/11/x/25-1638723135.jpg",
  "hentai": false,
  "sticky": false,
  "active": true,
  "actor": null,
  "malId": null,
  "aniId": null,
  "createdAt": "2021-12-05T20:16:16.000Z",
  "updatedAt": "2021-12-05T20:16:16.000Z",
  "deletedAt": null,
  "Mal": null,
  "Anilist": null,
  "malUrl": ""
}