{
  "authors": [
    "Gujira"
  ],
  "identifier": "manga-mb989736",
  "type": "manga",
  "page": "MangaNato",
  "title": "Himitsu No Reptiles",
  "url": "https://manganato.com/manga-mb989736",
  "image": "https://avt.mkklcdnv6temp.com/44/l/24-1633490880.jpg",
  "hentai": false,
  "sticky": false,
  "active": true,
  "actor": null,
  "malId": 98702,
  "aniId": 97272,
  "createdAt": "2021-10-06T05:02:28.000Z",
  "updatedAt": "2021-10-06T05:32:17.000Z",
  "deletedAt": null,
  "Mal": {
    "externalLinks": [],
    "altTitle": [
      "Reptile Secrets",
      "秘密のレプタイルズ"
    ],
    "authors": [
      "Gujira"
    ],
    "id": 98702,
    "type": "manga",
    "title": "Himitsu no Reptiles",
    "url": "https://myanimelist.net/manga/98702/Himitsu_no_Reptiles",
    "image": "https://cdn.myanimelist.net/images/manga/3/183545.jpg",
    "category": "Manga",
    "hentai": false,
    "createdAt": "2020-10-12T15:46:31.000Z",
    "updatedAt": "2021-10-06T05:02:47.000Z",
    "deletedAt": null
  },
  "Anilist": {
    "altTitle": [
      "Reptile Secrets",
      "秘密のレプタイルズ"
    ],
    "externalLinks": [],
    "authors": [
      "Gujira"
    ],
    "id": 97272,
    "malId": 98702,
    "type": "manga",
    "title": "Himitsu no Reptiles",
    "url": "https://anilist.co/manga/97272",
    "image": "https://s4.anilist.co/file/anilistcdn/media/manga/cover/medium/nx97272-iPJsYmEnH9MX.jpg",
    "category": "manga",
    "hentai": false,
    "createdAt": "2021-05-20T14:54:39.000Z",
    "updatedAt": "2021-07-12T22:15:02.000Z",
    "deletedAt": null
  },
  "malUrl": "https://myanimelist.net/manga/98702/Himitsu_no_Reptiles"
}