{
  "authors": [
    "Sakura Rico"
  ],
  "identifier": "manga-hl985020",
  "type": "manga",
  "page": "MangaNato",
  "title": "Ookami-Kun Wa Hanasanai",
  "url": "https://manganato.com/manga-hl985020",
  "image": "https://avt.mkklcdnv6temp.com/48/j/20-1585285078.jpg",
  "hentai": false,
  "sticky": false,
  "active": true,
  "actor": null,
  "malId": 129291,
  "aniId": 117534,
  "createdAt": "2021-05-31T09:47:03.000Z",
  "updatedAt": "2021-06-06T05:48:57.000Z",
  "deletedAt": null,
  "Mal": {
    "altTitle": [
      "Ookami-kun Won't Let Go",
      "オオカミくんははなさない"
    ],
    "authors": [
      "Sakura, Rico"
    ],
    "id": 129291,
    "type": "manga",
    "title": "Ookami-kun wa Hanasanai",
    "url": "https://myanimelist.net/manga/129291/Ookami-kun_wa_Hanasanai",
    "image": "https://cdn.myanimelist.net/images/manga/1/242490.jpg",
    "category": "Manga",
    "hentai": false,
    "createdAt": "2021-05-31T09:47:03.000Z",
    "updatedAt": "2021-05-31T09:47:03.000Z",
    "deletedAt": null
  },
  "Anilist": {
    "altTitle": [
      "オオカミくんははなさない",
      "I Won't Let Go of Ookami-kun"
    ],
    "authors": [
      "Riko Sakura"
    ],
    "id": 117534,
    "malId": 129291,
    "type": "manga",
    "title": "Ookami-kun wa Hanasanai",
    "url": "https://anilist.co/manga/117534",
    "image": "https://s4.anilist.co/file/anilistcdn/media/manga/cover/medium/bx117534-WlZcKKQugYcK.jpg",
    "category": "manga",
    "hentai": true,
    "createdAt": "2021-06-06T05:18:58.000Z",
    "updatedAt": "2021-06-06T05:18:58.000Z",
    "deletedAt": null
  },
  "malUrl": "https://myanimelist.net/manga/129291/Ookami-kun_wa_Hanasanai"
}