{
  "authors": [
    "Nonco"
  ],
  "identifier": "manga-je987139",
  "type": "manga",
  "page": "MangaNato",
  "title": "Youkai Izakaya Nonbereke",
  "url": "https://manganato.com/manga-je987139",
  "image": "https://avt.mkklcdnv6temp.com/35/g/22-1604682157.jpg",
  "hentai": false,
  "sticky": false,
  "active": true,
  "actor": null,
  "malId": 125142,
  "aniId": 108447,
  "createdAt": "2021-07-25T07:51:34.000Z",
  "updatedAt": "2021-07-25T08:21:34.000Z",
  "deletedAt": null,
  "Mal": {
    "altTitle": [
      "ようかい居酒屋 のんべれケ。"
    ],
    "authors": [
      "nonco"
    ],
    "id": 125142,
    "type": "manga",
    "title": "Youkai Izakaya Nonbereke.",
    "url": "https://myanimelist.net/manga/125142/Youkai_Izakaya_Nonbereke",
    "image": "https://cdn.myanimelist.net/images/manga/2/228169.jpg",
    "category": "Manga",
    "hentai": false,
    "createdAt": "2020-10-12T15:48:18.000Z",
    "updatedAt": "2021-07-25T07:52:26.000Z",
    "deletedAt": null
  },
  "Anilist": {
    "altTitle": [
      "ようかい居酒屋 のんべれケ。"
    ],
    "externalLinks": [],
    "authors": [
      "nonco"
    ],
    "id": 108447,
    "malId": 125142,
    "type": "manga",
    "title": "Youkai Izakaya Nonbereke.",
    "url": "https://anilist.co/manga/108447",
    "image": "https://s4.anilist.co/file/anilistcdn/media/manga/cover/medium/bx108447-6a1F2Q7DecHL.png",
    "category": "manga",
    "hentai": false,
    "createdAt": "2021-05-20T14:59:10.000Z",
    "updatedAt": "2021-06-18T05:54:34.000Z",
    "deletedAt": null
  },
  "malUrl": "https://myanimelist.net/manga/125142/Youkai_Izakaya_Nonbereke"
}