{
  "authors": [
    "Goto"
  ],
  "identifier": "manga-fc982611",
  "type": "manga",
  "page": "MangaNato",
  "title": "Sit, Wait, Kiss Me",
  "url": "https://manganato.com/manga-fc982611",
  "image": "https://avt.mkklcdnv6temp.com/8/b/19-1583499391.jpg",
  "hentai": false,
  "sticky": false,
  "active": true,
  "actor": null,
  "malId": null,
  "aniId": null,
  "createdAt": "2021-05-28T23:24:55.000Z",
  "updatedAt": "2021-05-28T23:24:55.000Z",
  "deletedAt": null,
  "Mal": null,
  "Anilist": null,
  "malUrl": ""
}