{
  "identifier": "m1xz",
  "type": "anime",
  "page": "9anime",
  "title": "MILPOM★",
  "url": "https://9anime.ru/watch/milpom.m1xz",
  "image": "http://static.akacdn.ru/static/images/2018/04/2920cba01042a08d1a358cfa7ce0b4bf.jpg",
  "hentai": false,
  "sticky": false,
  "active": true,
  "actor": null,
  "malId": 31471,
  "aniId": 100339,
  "createdAt": "2020-10-12T15:53:19.000Z",
  "updatedAt": "2021-05-20T15:21:51.000Z",
  "deletedAt": null,
  "Mal": {
    "altTitle": [
      "MILPOM★"
    ],
    "id": 31471,
    "type": "anime",
    "title": "MILPOM★",
    "url": "https://myanimelist.net/anime/31471/MILPOM★",
    "image": "https://cdn.myanimelist.net/images/anime/3/79018.jpg",
    "category": "ONA",
    "hentai": false,
    "createdAt": "2020-10-12T15:39:39.000Z",
    "updatedAt": "2021-04-30T15:48:43.000Z",
    "deletedAt": null
  },
  "Anilist": {
    "altTitle": [
      "MILPOM",
      "Milpom Star"
    ],
    "id": 100339,
    "malId": 31471,
    "type": "anime",
    "title": "MILPOM★",
    "url": "https://anilist.co/anime/100339",
    "image": "https://s4.anilist.co/file/anilistcdn/media/anime/cover/medium/nx100339-62UC6t29izPM.jpg",
    "category": "ona",
    "hentai": false,
    "createdAt": "2021-05-20T14:42:02.000Z",
    "updatedAt": "2021-05-20T14:42:02.000Z",
    "deletedAt": null
  },
  "malUrl": "https://myanimelist.net/anime/31471/MILPOM★"
}