{
  "identifier": "rv9m",
  "type": "anime",
  "page": "9anime",
  "title": "Honoo no Mirage (Dub)",
  "url": "https://9anime.ru/watch/honoo-no-mirage-dub.rv9m",
  "image": "https://images2-focus-opensocial.googleusercontent.com/gadgets/proxy?container=focus&amp;gadget=a&amp;no_expand=1&amp;refresh=604800&amp;url=http://2.bp.blogspot.com/-Tiig8ZgNYIw/WWJReNzmgpI/AAAAAAAAB2c/ebvsszavNfEzmJ277iNOkgsg7o00DFGDACHMYCw/s0/",
  "hentai": false,
  "sticky": false,
  "active": true,
  "actor": null,
  "malId": 1019,
  "aniId": 1019,
  "createdAt": "2020-10-12T15:55:36.000Z",
  "updatedAt": "2021-05-20T15:21:52.000Z",
  "deletedAt": null,
  "Mal": {
    "altTitle": [
      "Mirage of Blaze",
      "炎の蜃気楼 [ミラージュ]"
    ],
    "id": 1019,
    "type": "anime",
    "title": "Honoo no Mirage",
    "url": "https://myanimelist.net/anime/1019/Honoo_no_Mirage",
    "image": "https://cdn.myanimelist.net/images/anime/3/22614.jpg",
    "category": "TV",
    "hentai": false,
    "createdAt": "2020-10-12T15:38:11.000Z",
    "updatedAt": "2021-03-21T11:04:51.000Z",
    "deletedAt": null
  },
  "Anilist": {
    "altTitle": [
      "Mirage of Blaze",
      "炎の蜃気楼[ミラージュ]",
      "Honoo no Mirage"
    ],
    "id": 1019,
    "malId": 1019,
    "type": "anime",
    "title": "Honoo no Mirage",
    "url": "https://anilist.co/anime/1019",
    "image": "https://s4.anilist.co/file/anilistcdn/media/anime/cover/medium/1019.jpg",
    "category": "tv",
    "hentai": false,
    "createdAt": "2021-05-20T14:34:53.000Z",
    "updatedAt": "2021-05-20T14:34:53.000Z",
    "deletedAt": null
  },
  "malUrl": "https://myanimelist.net/anime/1019/Honoo_no_Mirage"
}