{
  "altTitle": [
    "異世界チート開拓記"
  ],
  "externalLinks": [],
  "authors": [
    "Minori Fuyuzora",
    "Fast"
  ],
  "id": 100639,
  "malId": 103980,
  "type": "manga",
  "title": "Isekai Cheat Kaitakuki",
  "url": "https://anilist.co/manga/100639",
  "image": "https://s4.anilist.co/file/anilistcdn/media/manga/cover/medium/bx100639-AsTK08AIFrx3.jpg",
  "category": "novel",
  "hentai": false,
  "createdAt": "2021-07-27T03:21:35.000Z",
  "updatedAt": "2021-07-27T03:21:35.000Z",
  "deletedAt": null,
  "Pages": {}
}