{
  "altTitle": [
    "Dの十字架",
    "Da Vinci's Golgotha",
    "D no Golgotha",
    "D no Gorugota"
  ],
  "authors": [
    "Hitoshi Imoto"
  ],
  "id": 103264,
  "malId": null,
  "type": "manga",
  "title": "D no Juujika",
  "url": "https://anilist.co/manga/103264",
  "image": "https://s4.anilist.co/file/anilistcdn/media/manga/cover/medium/nx103264-uFnQy4ttM6PT.jpg",
  "category": "manga",
  "hentai": false,
  "createdAt": "2021-06-11T05:08:19.000Z",
  "updatedAt": "2021-06-11T05:08:19.000Z",
  "deletedAt": null,
  "Pages": {}
}