{
  "altTitle": [
    "グレイヴヤードの捩じくれた家",
    "A Crooked Man in the Graveyard"
  ],
  "authors": [
    "Neri Iwasaki"
  ],
  "id": 107107,
  "malId": 120468,
  "type": "manga",
  "title": "Graveyard no Nejikureta Ie",
  "url": "https://anilist.co/manga/107107",
  "image": "https://s4.anilist.co/file/anilistcdn/media/manga/cover/medium/bx107107-q3PpVqu2NguI.jpg",
  "category": "manga",
  "hentai": false,
  "createdAt": "2021-05-20T14:58:15.000Z",
  "updatedAt": "2021-05-20T14:58:15.000Z",
  "deletedAt": null,
  "Pages": {
    "Mangadex": {
      "93b3234b-4687-47c1-8c98-fc53a112391c": {
        "authors": [
          "Iwasaki Neri"
        ],
        "identifier": "93b3234b-4687-47c1-8c98-fc53a112391c",
        "type": "manga",
        "page": "Mangadex",
        "title": "Graveyard no Nejikureta Ie",
        "url": "https://mangadex.org/title/93b3234b-4687-47c1-8c98-fc53a112391c",
        "image": "https://uploads.mangadex.org/covers/93b3234b-4687-47c1-8c98-fc53a112391c/9a8f29d7-2180-4078-b936-a4290c248997.jpg",
        "hentai": false,
        "sticky": false,
        "active": true,
        "actor": null,
        "malId": 120468,
        "aniId": 107107,
        "createdAt": "2020-10-12T16:15:58.000Z",
        "updatedAt": "2021-06-06T18:30:30.000Z",
        "deletedAt": null
      }
    }
  }
}