{
  "altTitle": [
    "놀러와 마이홈",
    "Come Over To My House And Play"
  ],
  "authors": [
    "Manmulsang"
  ],
  "id": 110428,
  "malId": null,
  "type": "manga",
  "title": "Nolleowa My Home",
  "url": "https://anilist.co/manga/110428",
  "image": "https://s4.anilist.co/file/anilistcdn/media/manga/cover/medium/bx110428-HbGiLmQpMDGz.png",
  "category": "manga",
  "hentai": false,
  "createdAt": "2021-06-06T03:49:38.000Z",
  "updatedAt": "2021-06-06T03:49:38.000Z",
  "deletedAt": null,
  "Pages": {
    "Mangadex": {
      "acdac9ac-2fd5-42b7-b3cb-034714ab0db6": {
        "authors": [
          "Manmul-sang"
        ],
        "identifier": "acdac9ac-2fd5-42b7-b3cb-034714ab0db6",
        "type": "manga",
        "page": "Mangadex",
        "title": "Come Over To My House And Play",
        "url": "https://mangadex.org/title/acdac9ac-2fd5-42b7-b3cb-034714ab0db6",
        "image": "https://uploads.mangadex.org/covers/acdac9ac-2fd5-42b7-b3cb-034714ab0db6/e99b0c75-66b8-4438-b1c2-8f734fdf06a7.png",
        "hentai": false,
        "sticky": false,
        "active": true,
        "actor": 1,
        "malId": null,
        "aniId": 110428,
        "createdAt": "2020-10-12T16:14:16.000Z",
        "updatedAt": "2021-06-06T10:07:32.000Z",
        "deletedAt": null
      }
    }
  }
}