{
  "altTitle": [
    "どうせ、恋してしまうんだ。",
    "Douse, Koishite Shimaunda"
  ],
  "authors": [
    "Haruka Mitsui"
  ],
  "id": 125855,
  "malId": 132739,
  "type": "manga",
  "title": "Douse, Koi shiteshimaunda.",
  "url": "https://anilist.co/manga/125855",
  "image": "https://s4.anilist.co/file/anilistcdn/media/manga/cover/medium/bx125855-VHFDI2KmfSG2.jpg",
  "category": "manga",
  "hentai": false,
  "createdAt": "2021-05-20T15:00:10.000Z",
  "updatedAt": "2021-06-08T06:50:50.000Z",
  "deletedAt": null,
  "Pages": {
    "Mangadex": {
      "805c67ad-7508-4aff-a216-011abd86b06c": {
        "authors": [
          "Mitsui Haruka"
        ],
        "identifier": "805c67ad-7508-4aff-a216-011abd86b06c",
        "type": "manga",
        "page": "Mangadex",
        "title": "Douse, Koishite Shimaunda",
        "url": "https://mangadex.org/title/805c67ad-7508-4aff-a216-011abd86b06c",
        "image": "https://uploads.mangadex.org/covers/805c67ad-7508-4aff-a216-011abd86b06c/0c8221cf-fde2-4c29-8517-8feb8feb9763.jpg",
        "hentai": false,
        "sticky": false,
        "active": true,
        "actor": 1,
        "malId": 132739,
        "aniId": 125855,
        "createdAt": "2020-11-04T03:24:55.000Z",
        "updatedAt": "2021-06-08T06:51:14.000Z",
        "deletedAt": null
      }
    },
    "MangaNelo": {
      "gi925213": {
        "authors": [
          "Mitsui",
          "Haruka"
        ],
        "identifier": "gi925213",
        "type": "manga",
        "page": "MangaNelo",
        "title": "Douse, Koishite Shimaunda",
        "url": "https://manganelo.com/manga/gi925213",
        "image": "https://avt.mkklcdnv6temp.com/7/u/23-1610872337.jpg",
        "hentai": false,
        "sticky": false,
        "active": true,
        "actor": null,
        "malId": 132739,
        "aniId": 125855,
        "createdAt": "2021-05-02T18:33:43.000Z",
        "updatedAt": "2021-05-20T15:40:50.000Z",
        "deletedAt": null
      }
    },
    "MangaNato": {
      "manga-kz987682": {
        "authors": [
          "Mitsui Haruka"
        ],
        "identifier": "manga-kz987682",
        "type": "manga",
        "page": "MangaNato",
        "title": "Douse, Koishite Shimaunda",
        "url": "https://manganato.com/manga-kz987682",
        "image": "https://avt.mkklcdnv6temp.com/7/u/23-1610872337.jpg",
        "hentai": false,
        "sticky": false,
        "active": true,
        "actor": null,
        "malId": 132739,
        "aniId": 125855,
        "createdAt": "2021-06-03T06:01:36.000Z",
        "updatedAt": "2021-06-03T06:30:50.000Z",
        "deletedAt": null
      }
    }
  }
}