{
  "altTitle": [
    "7年目の純愛",
    "Junku & Ai, Together for 7 Years"
  ],
  "authors": [
    "Youko Fujitani"
  ],
  "id": 131059,
  "malId": 133113,
  "type": "manga",
  "title": "7-nenme no Junai",
  "url": "https://anilist.co/manga/131059",
  "image": "https://s4.anilist.co/file/anilistcdn/media/manga/cover/medium/bx131059-ra6cZTyubYxk.jpg",
  "category": "manga",
  "hentai": false,
  "createdAt": "2021-06-12T09:38:19.000Z",
  "updatedAt": "2021-06-12T09:38:19.000Z",
  "deletedAt": null,
  "Pages": {}
}