{
  "altTitle": [
    "天穂のサクナヒメ ココロワ稲作日誌"
  ],
  "externalLinks": [],
  "authors": [
    "Keiji  Andou",
    "Edelweiss",
    "Edelweiss"
  ],
  "id": 137789,
  "malId": null,
  "type": "manga",
  "title": "Tensui no Sakuna-hime: Kokorowa Inasaku Nisshi",
  "url": "https://anilist.co/manga/137789",
  "image": "https://s4.anilist.co/file/anilistcdn/media/manga/cover/medium/bx137789-Yh61HCeRraaX.jpg",
  "category": "novel",
  "hentai": false,
  "createdAt": "2021-08-11T00:09:16.000Z",
  "updatedAt": "2021-08-11T00:09:16.000Z",
  "deletedAt": null,
  "Pages": {}
}