{
  "altTitle": [
    "Please, Don't Livestream It!",
    "学姐，不要直播出去！"
  ],
  "externalLinks": [],
  "authors": [
    "Yu Zhou",
    "Leng Chang Shi Fa Zhe"
  ],
  "id": 138091,
  "malId": null,
  "type": "manga",
  "title": "Xuejie, Buyao Zhibo Chuqu!",
  "url": "https://anilist.co/manga/138091",
  "image": "https://s4.anilist.co/file/anilistcdn/media/manga/cover/medium/bx138091-Ehg50X8wFKaF.jpg",
  "category": "manga",
  "hentai": false,
  "createdAt": "2021-08-19T06:37:07.000Z",
  "updatedAt": "2021-11-07T11:47:47.000Z",
  "deletedAt": null,
  "Pages": {
    "Mangadex": {
      "329cf43e-8e0c-4984-95c8-5df22aca1aa1": {
        "authors": [
          "冷场施法者"
        ],
        "identifier": "329cf43e-8e0c-4984-95c8-5df22aca1aa1",
        "type": "manga",
        "page": "Mangadex",
        "title": "Xuejie, Don't Livestream It!",
        "url": "https://mangadex.org/title/329cf43e-8e0c-4984-95c8-5df22aca1aa1",
        "image": "https://uploads.mangadex.org/covers/329cf43e-8e0c-4984-95c8-5df22aca1aa1/b7d56fc3-b46f-4958-b3b3-ab45e37e894f.jpg",
        "hentai": false,
        "sticky": false,
        "active": true,
        "actor": 1,
        "malId": null,
        "aniId": 138091,
        "createdAt": "2020-10-12T16:21:10.000Z",
        "updatedAt": "2021-11-07T22:46:12.000Z",
        "deletedAt": null
      }
    }
  }
}