{
  "altTitle": [
    "落第忍者乱太郎"
  ],
  "authors": [
    "Soubee Amako"
  ],
  "id": 41127,
  "malId": 11127,
  "type": "manga",
  "title": "Rakudai Ninja RANTARO",
  "url": "https://anilist.co/manga/41127",
  "image": "https://s4.anilist.co/file/anilistcdn/media/manga/cover/medium/11127.jpg",
  "category": "manga",
  "hentai": false,
  "createdAt": "2021-05-20T14:41:15.000Z",
  "updatedAt": "2021-05-20T14:41:15.000Z",
  "deletedAt": null,
  "Pages": {
    "Mangadex": {
      "cb2ed96a-1a91-4f72-9dfd-d6cfb3b587d4": {
        "authors": [
          "AMAKO Soubee"
        ],
        "identifier": "cb2ed96a-1a91-4f72-9dfd-d6cfb3b587d4",
        "type": "manga",
        "page": "Mangadex",
        "title": "Rakudai Ninja Rantarou",
        "url": "https://mangadex.org/title/cb2ed96a-1a91-4f72-9dfd-d6cfb3b587d4",
        "image": "https://uploads.mangadex.org/covers/cb2ed96a-1a91-4f72-9dfd-d6cfb3b587d4/a8d3a799-0f48-42b3-b62e-3a8863d00cb7.jpg",
        "hentai": false,
        "sticky": false,
        "active": true,
        "actor": null,
        "malId": 11127,
        "aniId": 41127,
        "createdAt": "2020-10-12T16:05:03.000Z",
        "updatedAt": "2021-06-03T09:57:58.000Z",
        "deletedAt": null
      }
    }
  }
}