{
  "altTitle": [
    "Green Peace",
    "グリーン・ピース"
  ],
  "authors": [
    "Kyou Kitazawa"
  ],
  "id": 44289,
  "malId": 14289,
  "type": "manga",
  "title": "Green Peace",
  "url": "https://anilist.co/manga/44289",
  "image": "https://s4.anilist.co/file/anilistcdn/media/manga/cover/medium/14289.jpg",
  "category": "manga",
  "hentai": false,
  "createdAt": "2021-05-20T14:42:45.000Z",
  "updatedAt": "2021-05-20T14:42:45.000Z",
  "deletedAt": null,
  "Pages": {
    "Mangadex": {
      "4aaea7fc-6f89-44f6-a26c-5ff45bd9484a": {
        "authors": [
          "Kitazawa Kyou"
        ],
        "identifier": "4aaea7fc-6f89-44f6-a26c-5ff45bd9484a",
        "type": "manga",
        "page": "Mangadex",
        "title": "Green Peace",
        "url": "https://mangadex.org/title/4aaea7fc-6f89-44f6-a26c-5ff45bd9484a",
        "image": "https://uploads.mangadex.org/covers/4aaea7fc-6f89-44f6-a26c-5ff45bd9484a/d12e585a-1664-4ded-96d8-1f3dcef23041.jpg",
        "hentai": false,
        "sticky": false,
        "active": true,
        "actor": null,
        "malId": 14289,
        "aniId": 44289,
        "createdAt": "2020-10-12T16:13:16.000Z",
        "updatedAt": "2021-06-05T20:01:53.000Z",
        "deletedAt": null
      }
    }
  }
}