{
  "altTitle": [
    "終電にはかえします",
    "Return by the Last Train",
    "Shuuden niwa Kaeshimasu",
    "From Aiu Station on the Hiragana Line",
    "I’ll send her home on the last train"
  ],
  "externalLinks": [],
  "authors": [
    "Gido Amagakure"
  ],
  "id": 85662,
  "malId": 67099,
  "type": "manga",
  "title": "Shuuden ni wa Kaeshimasu",
  "url": "https://anilist.co/manga/85662",
  "image": "https://s4.anilist.co/file/anilistcdn/media/manga/cover/medium/bx85662-y1oCYMQubhuy.jpg",
  "category": "manga",
  "hentai": false,
  "createdAt": "2021-05-20T14:50:59.000Z",
  "updatedAt": "2021-06-17T21:54:00.000Z",
  "deletedAt": null,
  "Pages": {
    "Mangadex": {
      "ca6de29f-58ae-448a-bbbc-f80819eefcc3": {
        "authors": [
          "Amagakure Gido"
        ],
        "identifier": "ca6de29f-58ae-448a-bbbc-f80819eefcc3",
        "type": "manga",
        "page": "Mangadex",
        "title": "Shuuden ni wa Kaeshimasu",
        "url": "https://mangadex.org/title/ca6de29f-58ae-448a-bbbc-f80819eefcc3",
        "image": "https://uploads.mangadex.org/covers/ca6de29f-58ae-448a-bbbc-f80819eefcc3/f551301d-cba9-48fe-9cd2-e692d1cf4e66.jpg",
        "hentai": false,
        "sticky": false,
        "active": true,
        "actor": null,
        "malId": 67099,
        "aniId": 85662,
        "createdAt": "2020-10-12T16:04:11.000Z",
        "updatedAt": "2021-06-02T19:19:32.000Z",
        "deletedAt": null
      }
    },
    "MangaNato": {
      "manga-uk953419": {
        "authors": [
          "Amagakure Gido"
        ],
        "identifier": "manga-uk953419",
        "type": "manga",
        "page": "MangaNato",
        "title": "Shuuden Ni Wa Kaeshimasu",
        "url": "https://manganato.com/manga-uk953419",
        "image": "https://avt.mkklcdnv6temp.com/22/q/2-1583466581.jpg",
        "hentai": false,
        "sticky": false,
        "active": true,
        "actor": null,
        "malId": 67099,
        "aniId": 85662,
        "createdAt": "2021-07-27T02:51:50.000Z",
        "updatedAt": "2021-07-27T03:21:35.000Z",
        "deletedAt": null
      }
    }
  }
}