{
  "altTitle": [
    "Sound in the future after seven seconds",
    "7秒後の酒多さんと、俺。",
    "Nanabyougo no Sakata-san to",
    "Ore."
  ],
  "externalLinks": [],
  "authors": [
    "Kouta Asanuma",
    "Koma Amezawa"
  ],
  "id": 92593,
  "malId": 77943,
  "type": "manga",
  "title": "7-byougo no Sakata-san to, Ore.",
  "url": "https://anilist.co/manga/92593",
  "image": "https://s4.anilist.co/file/anilistcdn/media/manga/cover/medium/bx92593-ubn0JeK7PK8m.jpg",
  "category": "novel",
  "hentai": false,
  "createdAt": "2021-07-18T23:32:31.000Z",
  "updatedAt": "2021-07-18T23:32:31.000Z",
  "deletedAt": null,
  "Pages": {}
}