{
  "altTitle": [
    "ファイナルファンタジーXIII-2 Fragments Before"
  ],
  "externalLinks": [],
  "authors": [],
  "id": 92928,
  "malId": 79931,
  "type": "manga",
  "title": "Final Fantasy XIII-2: Fragments Before",
  "url": "https://anilist.co/manga/92928",
  "image": "https://s4.anilist.co/file/anilistcdn/media/manga/cover/medium/92928-y8mBfcSp7hQr.jpg",
  "category": "novel",
  "hentai": false,
  "createdAt": "2021-07-18T11:02:22.000Z",
  "updatedAt": "2021-07-18T11:02:22.000Z",
  "deletedAt": null,
  "Pages": {}
}